Workbook

Sheet Competitor Analsyis_Ratios
B1: PAT (10-yr avg) | C1: Shareholder's Equity | D1: ROE | E1: Sales | F1: Net profit margin | G1: Total borrowings(debt) | H1: Debt-to-Equity Ratio | I1: Debtor Days | J1: Revenue Growth
A2: Asian Paints | B2: =AVERAGE('Asian Paints_Ratios'!B2:K2) -> 2837.1 | C2: 10822 | D2: =AVERAGE('Asian Paints_Ratios'!B9:K9) -> 26.316885 | E2: 21992 | F2: 13 | G2: 1135 | H2: 0.1 | I2: 39 | J2: 0.12
A3: BergerPaints | B3: ='Berger Paints_Ratios'!L2 -> 630.4 | C3: 2919 | D3: ='Berger Paints_Ratios'!L4 -> 21.511949 | E3: 6788 | F3: 9 | G3: 473 | H3: 0.2 | I3: 45 | J3: 0.12
A4: Kansai Nerolac | B4: ='Kansai Nerolac_Ratios'!L2 -> 627.3 | C4: 3553 | D4: ='Kansai Nerolac_Ratios'!L4 -> 16.91647 | E4: 5347 | F4: 11 | G4: 105 | H4: 0.03 | I4: 57 | J4: 0.1

Sheet Phase 1_Balance sheet
B1: FY 2014 | C1: FY 2015 | D1: FY 2016 | E1: FY 2017 | F1: FY 2018 | G1: FY 2019 | H1: FY 2020 | I1: FY 2021 | J1: FY 2022 | K1: FY 2023 | L1: FY 2024
A2: Total Assets | B2: 8075 | C2: 8914 | D2: 10559 | E2: 12405 | F2: 13763 | G2: 16249 | H2: 16138 | I2: 20355 | J2: 22958 | K2: 25779 | L2: 29901
A3: Total Liabilities | B3: 8075 | C3: 8914 | D3: 10559 | E3: 12405 | F3: 13763 | G3: 16249 | H3: 16138 | I3: 20355 | J3: 22958 | K3: 25779 | L3: 29901
A4: Shareholder's Equity | B4: =(96+3943) -> 4039 | C4: =(96+4646) -> 4742 | D4: =(96+6429) -> 6525 | E4: =(96+7508) -> 7604 | F4: =(96+8314) -> 8410 | G4: =(96+9374) -> 9470 | H4: =(96+10035) -> 10131 | I4: =(96+12710) -> 12806 | J4: =(96+13715) -> 13811 | K4: =(96+15896) -> 15992 | L4: =(96+18633) -> 18729
A5: Other Liabilities | B5: 3787 | C5: 3754 | D5: 3711 | E5: 4241 | F5: 4820 | G5: 5459 | H5: 4889 | I5: 6456 | J5: 7560 | K5: 7854 | L5: 8698
A6: Borrowings | B6: 249 | C6: 418 | D6: 323 | E6: 560 | F6: 533 | G6: 1320 | H6: 1118 | I6: 1093 | J6: 1587 | K6: 1933 | L6: 2474
A7: Balance Check | B7: =B2-(B4+B6+B5) -> 0 | C7: =C2-(C4+C6+C5) -> 0 | D7: =D2-(D4+D6+D5) -> 0 | E7: =E2-(E4+E6+E5) -> 0 | F7: =F2-(F4+F6+F5) -> 0 | G7: =G2-(G4+G6+G5) -> 0 | H7: =H2-(H4+H6+H5) -> 0 | I7: =I2-(I4+I6+I5) -> 0 | ... L7: =L2-(L4+L6+L5) -> 0

Sheet Phase 1_Income Statement
B1: FY 2015 | C1: FY 2016 | D1: FY 2017 | E1: FY 2018 | F1: FY 2019 | G1: FY 2020 | H1: FY 2021 | I1: FY 2022 | J1: FY 2023 | K1: FY 2024
A2: Revenue | B2: 13615 | C2: 14271 | D2: 15062 | E2: 16825 | F2: 19240 | G2: 20211 | H2: 21713 | I2: 29101 | J2: 34389 | K2: 35495
A3: (−) Material Cost | B3: 6875 | C3: 6570 | D3: 7453 | E3: 8128 | F3: 9974 | G3: 9982 | H3: 10426 | I3: 17123 | J3: 18986 | K3: 17411
A4: Gross Profit | B4: =B2-B3 -> 6740 | C4: =C2-C3 -> 7701 | D4: =D2-D3 -> 7609 | E4: =E2-E3 -> 8697 | F4: =F2-F3 -> 9266 | G4: =G2-G3 -> 10229 | H4: =H2-H3 -> 11287 | I4: =I2-I3 -> 11978 | ... K4: =K2-K3 -> 18084
A5: (−) Other Operating Expense | B5: =B2-B3-B6 -> 4497 | C5: =C2-C3-C6 -> 4976 | D5: =D2-D3-D6 -> 4615 | E5: =E2-E3-E6 -> 5493 | F5: =F2-F3-F6 -> 5501 | G5: =G2-G3-G6 -> 6067 | H5: =H2-H3-H6 -> 6431 | I5: =I2-I3-I6 -> 7174 | ... K5: =K2-K3-K6 -> 10499
A6: EBITDA | B6: 2243 | C6: 2725 | D6: 2994 | E6: 3204 | F6: 3765 | G6: 4162 | H6: 4856 | I6: 4804 | J6: 6260 | K6: 7585
A7: (−) Depreciation | B7: 266 | C7: 276 | D7: 335 | E7: 360 | F7: 622 | G7: 780 | H7: 791 | I7: 816 | J7: 858 | K7: 853
A8: EBIT | B8: =B6-B7 -> 1977 | C8: =C6-C7 -> 2449 | D8: =D6-D7 -> 2659 | E8: =E6-E7 -> 2844 | F8: =F6-F7 -> 3143 | G8: =G6-G7 -> 3382 | H8: =H6-H7 -> 4065 | I8: =I6-I7 -> 3988 | ... K8: =K6-K7 -> 6732
A9: (−) Interest | B9: 42 | C9: 49 | D9: 37 | E9: 41 | F9: 110 | G9: 102 | H9: 92 | I9: 95 | J9: 144 | K9: 205
A10: PBT | B10: =B8-B9 -> 1935 | C10: =C8-C9 -> 2400 | D10: =D8-D9 -> 2622 | E10: =E8-E9 -> 2803 | F10: =F8-F9 -> 3033 | G10: =G8-G9 -> 3280 | H10: =H8-H9 -> 3973 | I10: =I8-I9 -> 3893 | ... K10: =K8-K9 -> 6527
A11: (−) Tax | B11: =B10-B12 -> 508 | C11: =C10-C12 -> 597 | D11: =D10-D12 -> 606 | E11: =E10-E12 -> 705 | F11: =F10-F12 -> 825 | G11: =G10-G12 -> 506 | H11: =H10-H12 -> 766 | I11: =I10-I12 -> 808 | ... K11: =K10-K12 -> 969
A12: PAT | B12: 1427 | C12: 1803 | D12: 2016 | E12: 2098 | F12: 2208 | G12: 2774 | H12: 3207 | I12: 3085 | J12: 4195 | K12: 5558

Sheet Berger Paints_Ratios
B1: FY 2015 | C1: FY 2016 | D1: FY 2017 | E1: FY 2018 | F1: FY 2019 | G1: FY 2020 | H1: FY 2021 | I1: FY 2022 | J1: FY 2023 | K1: FY 2024 | L1: Average
A2: PAT | B2: 265 | C2: 371 | D2: 474 | E2: 461 | F2: 494 | G2: 656 | H2: 720 | I2: 833 | J2: 860 | K2: 1170 | L2: =AVERAGE(B2:K2) -> 630.4
A3: Shareholder's Equity | B3: =(69+1191) -> 1260 | C3: =(69+1493) -> 1562 | D3: =(97+1804) -> 1901 | E3: =(98+2097) -> 2195 | F3: =(97+2347) -> 2444 | G3: =(91+2563) -> 2654 | H3: =(97+3280) -> 3377 | I3: =(97+3830) -> 3927 | J3: =(97+4397) -> 4494 | K3: =(117+5262) -> 5379 | L3: =AVERAGE(B3:K3) -> 2919.3
A4: ROE | B4: =(B2/B3)*100 -> 21.031746 | C4: =(C2/C3)*100 -> 23.751601 | D4: =(D2/D3)*100 -> 24.934245 | E4: =(E2/E3)*100 -> 21.002278 | F4: =(F2/F3)*100 -> 20.212766 | G4: =(G2/G3)*100 -> 24.717408 | H4: =(H2/H3)*100 -> 21.320699 | I4: =(I2/I3)*100 -> 21.212121 | J4: =(J2/J3)*100 -> 19.136627 | K4: 17.8 | L4: =AVERAGE(B4:K4) -> 21.511949
A5: Sales | B5: 4170 | C5: 4223 | D5: 4552 | E5: 5166 | F5: 6062 | G5: 6366 | H5: 6818 | I5: 8762 | J5: 10568 | K5: 11199 | L5: =AVERAGE(B5:K5) -> 6788.6
A6: Net profit margin | B6: =B2/B5*100 -> 6.3549161 | C6: =C2/C5*100 -> 8.7852238 | D6: =D2/D5*100 -> 10.413005 | E6: =E2/E5*100 -> 8.9237321 | F6: =F2/F5*100 -> 8.1491257 | G6: =G2/G5*100 -> 10.304744 | H6: =H2/H5*100 -> 10.560282 | I6: =I2/I5*100 -> 9.5069619 | ... K6: =K2/K5*100 -> 10.447361 | L6: =AVERAGE(B6:K6) -> 9.1583126
A7: Total borrowings(debt) | B7: =(251+358) -> 609 | C7: =(211+99) -> 310 | D7: =(262+144) -> 406 | E7: =(249+173) -> 422 | F7: =(239+245) -> 484 | G7: =(239+245) -> 484 | H7: =(166+210) -> 376 | I7: =(10+658) -> 668 | J7: =(8+760) -> 768 | K7: =(6+199) -> 205 | L7: =AVERAGE(B7:K7) -> 473.2
A8: Debt-to-Equity ratio | B8: =B7/B3 -> 0.48333333 | C8: =C7/C3 -> 0.19846351 | D8: =D7/D3 -> 0.2135718 | E8: =E7/E3 -> 0.19225513 | F8: =F7/F3 -> 0.19803601 | G8: =G7/G3 -> 0.18236624 | H8: =H7/H3 -> 0.11134143 | I8: =I7/I3 -> 0.17010441 | ... K8: =K7/K3 -> 0.038111173 | L8: =AVERAGE(B8:K8) -> 0.19584775
A9: Debtor Days | B9: 47 | C9: 47 | D9: 46 | E9: 49 | F9: 40 | G9: 41 | H9: 55 | I9: 44 | J9: 43 | K9: 42 | L9: =AVERAGE(B9:K9) -> 45.4
A10: Revenue Growth | C10: =(C5-B5)/B5 -> 0.012709832 | D10: =(D5-C5)/C5 -> 0.077906701 | E10: =(E5-D5)/D5 -> 0.13488576 | F10: =(F5-E5)/E5 -> 0.17344173 | G10: =(G5-F5)/F5 -> 0.050148466 | H10: =(H5-G5)/G5 -> 0.071002199 | I10: =(I5-H5)/H5 -> 0.2851276 | J10: =(J5-I5)/I5 -> 0.20611732 | K10: =(K5-J5)/J5 -> 0.059708554 | L10: =AVERAGE(B10:K10) -> 0.11900535

Sheet Kansai Nerolac_Ratios
B1: FY 2015 | C1: FY 2016 | D1: FY 2017 | E1: FY 2018 | F1: FY 2019 | G1: FY 2020 | H1: FY 2021 | I1: FY 2022 | J1: FY 2023 | K1: FY 2024 | L1: Average
A2: PAT | B2: 275 | C2: 902 | D2: 510 | E2: 448 | F2: 516 | G2: 526 | H2: 343 | I2: 468 | J2: 1176 | K2: 1109 | L2: =AVERAGE(B2:K2) -> 627.3
A3: Shareholder's equity | B3: =(54+1548) -> 1602 | C3: =(54+2456) -> 2510 | D3: =(54+2761) -> 2815 | E3: =(54+3078) -> 3132 | F3: =(54+3362) -> 3416 | G3: =(54+3706) -> 3760 | H3: =(54+3999) -> 4053 | I3: =(54+4078) -> 4132 | J3: =(54+4480) -> 4534 | K3: =(81+5502) -> 5583 | L3: =AVERAGE(B3:K3) -> 3553.7
A4: ROE | B4: =(B2/B3)*100 -> 17.166042 | C4: =(C2/C3)*100 -> 35.936255 | D4: =(D2/D3)*100 -> 18.117229 | E4: =(E2/E3)*100 -> 14.303959 | F4: =(F2/F3)*100 -> 15.105386 | G4: =(G2/G3)*100 -> 13.989362 | H4: =(H2/H3)*100 -> 8.462867 | I4: =(I2/I3)*100 -> 11.326234 | J4: =(J2/J3)*100 -> 25.937362 | K4: 8.82 | L4: =AVERAGE(B4:K4) -> 16.91647
A5: Sales | B5: 3505 | C5: 3767 | D5: 4053 | E5: 4658 | F5: 5424 | G5: 5280 | H5: 5074 | I5: 6369 | J5: 7543 | K5: 7801 | L5: =AVERAGE(B5:K5) -> 5347.4
A6: Net profit margin | B6: =B2/B5*100 -> 7.8459344 | C6: =C2/C5*100 -> 23.944784 | D6: =D2/D5*100 -> 12.583272 | E6: =E2/E5*100 -> 9.6178617 | F6: =F2/F5*100 -> 9.5132743 | G6: =G2/G5*100 -> 9.9621212 | H6: =H2/H5*100 -> 6.7599527 | I6: =I2/I5*100 -> 7.3480923 | ... K6: =K2/K5*100 -> 14.216126 | L6: =AVERAGE(B6:K6) -> 11.738203
A7: Total borrowings(debt) | B7: =(46+4) -> 50 | C7: =(29+0) -> 29 | D7: =(18+0) -> 18 | E7: =(10+17) -> 27 | F7: =(4+97) -> 101 | G7: =(23+150) -> 173 | H7: =(17+150) -> 167 | I7: =(11+192) -> 203 | J7: =(5+155) -> 160 | K7: =(15+106) -> 121 | L7: =AVERAGE(B7:K7) -> 104.9
A8: Debt-to-equity ratio | B8: =B7/B3 -> 0.031210986 | C8: =C7/C3 -> 0.011553785 | D8: =D7/D3 -> 0.0063943162 | E8: =E7/E3 -> 0.0086206897 | F8: =F7/F3 -> 0.029566745 | G8: =G7/G3 -> 0.046010638 | H8: =H7/H3 -> 0.041204046 | I8: =I7/I3 -> 0.049128751 | ... K8: =K7/K3 -> 0.021672936 | L8: =AVERAGE(B8:K8) -> 0.028065182
A9: Debtor's Days | B9: 54 | C9: 53 | D9: 53 | E9: 55 | F9: 51 | G9: 54 | H9: 69 | I9: 63 | J9: 60 | K9: 62 | L9: =AVERAGE(B9:K9) -> 57.4
A10: Revenue Growth | C10: =(C5-B5)/B5 -> 0.074750357 | D10: =(D5-C5)/C5 -> 0.075922485 | E10: =(E5-D5)/D5 -> 0.14927214 | F10: =(F5-E5)/E5 -> 0.16444826 | G10: =(G5-F5)/F5 -> -0.026548673 | H10: =(H5-G5)/G5 -> -0.039015152 | I10: =(I5-H5)/H5 -> 0.2552227 | J10: =(J5-I5)/I5 -> 0.18433035 | K10: =(K5-J5)/J5 -> 0.034203898 | L10: =AVERAGE(B10:K10) -> 0.096954042

Sheet Asian Paints_Ratios
B1: FY 2015 | C1: FY 2016 | D1: FY 2017 | E1: FY 2018 | F1: FY 2019 | G1: FY 2020 | H1: FY 2021 | I1: FY 2022 | J1: FY 2023 | K1: FY 2024
A2: PAT | B2: 1427 | C2: 1803 | D2: 2016 | E2: 2098 | F2: 2208 | G2: 2774 | H2: 3207 | I2: 3085 | J2: 4195 | K2: 5558
A3: Shareholder's Equity | B3: =(96+4646) -> 4742 | C3: =(96+6429) -> 6525 | D3: =(96+7508) -> 7604 | E3: =(96+8314) -> 8410 | F3: =(96+9374) -> 9470 | G3: =(96+10035) -> 10131 | H3: =(96+12710) -> 12806 | I3: =(96+13715) -> 13811 | J3: =(96+15896) -> 15992 | K3: =(96+18633) -> 18729
A4: Total Assets | B4: 8914 | C4: 10559 | D4: 12405 | E4: 13763 | F4: 16249 | G4: 16138 | H4: 20355 | I4: 22958 | J4: 25779 | K4: 29901
A5: PBT | B5: 1935 | C5: 2400 | D5: 2622 | E5: 2803 | F5: 3033 | G5: 3280 | H5: 3973 | I5: 4065 | J5: 3988 | K5: 5402
A6: Interest | B6: 42 | C6: 49 | D6: 37 | E6: 41 | F6: 110 | G6: 102 | H6: 92 | I6: 95 | J6: 144 | K6: 205
A7: EBIT | B7: 1977 | C7: 2449 | D7: 2659 | E7: 2844 | F7: 3143 | G7: 3382 | H7: 4065 | I7: 3988 | J7: 5402 | K7: 6732
A8: Other Liabilities | B8: 3754 | C8: 3711 | D8: 4241 | E8: 4820 | F8: 5459 | G8: 4889 | H8: 6456 | I8: 7560 | J8: 7854 | K8: 8698
A9: ROE | B9: =B2/B3*100 -> 30.092788 | C9: =C2/C3*100 -> 27.632184 | D9: =D2/D3*100 -> 26.512362 | E9: =E2/E3*100 -> 24.946492 | F9: =F2/F3*100 -> 23.315734 | G9: =G2/G3*100 -> 27.381305 | H9: =H2/H3*100 -> 25.042949 | I9: =I2/I3*100 -> 22.337267 | ... K9: =K2/K3*100 -> 29.675904
A10: ROA | B10: =B2/B4*100 -> 16.008526 | C10: =C2/C4*100 -> 17.075481 | D10: =D2/D4*100 -> 16.251511 | E10: =E2/E4*100 -> 15.24377 | F10: =F2/F4*100 -> 13.588529 | G10: =G2/G4*100 -> 17.189243 | H10: =H2/H4*100 -> 15.755343 | I10: =I2/I4*100 -> 13.437582 | ... K10: =K2/K4*100 -> 18.588007
A11: ROCE | B11: =B7/(B4-B8) -> 0.38313953 | C11: =C7/(C4-C8) -> 0.35762266 | D11: =D7/(D4-D8) -> 0.32569819 | E11: =E7/(E4-E8) -> 0.31801409 | F11: =F7/(F4-F8) -> 0.29128823 | G11: =G7/(G4-G8) -> 0.30064895 | H11: =H7/(H4-H8) -> 0.29246708 | I11: =I7/(I4-I8) -> 0.25899467 | ... K11: =K7/(K4-K8) -> 0.31750224
A12: Total Borrowings | B12: 418 | C12: 323 | D12: 560 | E12: 533 | F12: 1320 | G12: 1118 | H12: 1093 | I12: 1587 | J12: 1933 | K12: 2474
A13: Interest Coverage | B13: =B7/B6 -> 47.071429 | C13: =C7/C6 -> 49.979592 | D13: =D7/D6 -> 71.864865 | E13: =E7/E6 -> 69.365854 | F13: =F7/F6 -> 28.572727 | G13: =G7/G6 -> 33.156863 | H13: =H7/H6 -> 44.184783 | I13: =I7/I6 -> 41.978947 | ... K13: =K7/K6 -> 32.839024
A14: EBITDA | B14: 2243 | C14: 2725 | D14: 2994 | E14: 3204 | F14: 3765 | G14: 4162 | H14: 4856 | I14: 4804 | J14: 6260 | K14: 7585 | N14: 0
A15: Revenue | B15: 13615 | C15: 14271 | D15: 15062 | E15: 16825 | F15: 19240 | G15: 20211 | H15: 21713 | I15: 29101 | J15: 34389 | K15: 35495
A16: Operating Margin | B16: =B14/B15*100 -> 16.474477 | C16: =C14/C15*100 -> 19.094668 | D16: =D14/D15*100 -> 19.877838 | E16: =E14/E15*100 -> 19.043091 | F16: =F14/F15*100 -> 19.568607 | G16: =G14/G15*100 -> 20.592747 | H16: =H14/H15*100 -> 22.364482 | I16: =I14/I15*100 -> 16.508024 | ... K16: =K14/K15*100 -> 21.369207
A17: Net Profit Margin | B17: =B2/B15*100 -> 10.481087 | C17: =C2/C15*100 -> 12.634013 | D17: =D2/D15*100 -> 13.384677 | E17: =E2/E15*100 -> 12.469539 | F17: =F2/F15*100 -> 11.476091 | G17: =G2/G15*100 -> 13.725199 | H17: =H2/H15*100 -> 14.769953 | I17: =I2/I15*100 -> 10.60101 | ... K17: =K2/K15*100 -> 15.658543
A18: Trade Receivables | B18: -155 | C18: -146 | D18: -475 | E18: -483 | F18: -205 | G18: 160 | H18: -849 | I18: -1326 | J18: -834 | K18: -362
A19: Trade Payables | B19: -151 | C19: 142 | D19: 501 | E19: 442 | F19: 287 | G19: -241 | H19: 1143 | I19: 644 | J19: -539 | K19: 269
A20: Inventory | B20: -144 | C20: 202 | D20: -629 | E20: -39 | F20: -492 | G20: -251 | H20: -409 | I20: -2354 | J20: -56 | K20: 315
A21: Material Costs | B21: 6875 | C21: 6570 | D21: 7453 | E21: 8128 | F21: 9974 | G21: 9982 | H21: 10426 | I21: 17123 | J21: 18986 | K21: 17411
A22: Debtor Days | B22: 32 | C22: 30 | D22: 35 | E22: 38 | F22: 36 | G22: 32 | H22: 44 | I22: 49 | J22: 49 | K22: 46
A23: Inventory Days | B23: 123 | C23: 108 | D23: 138 | E23: 117 | F23: 119 | G23: 127 | H23: 134 | I23: 142 | J23: 121 | K23: 122
A24: Days Payable | B24: 84 | C24: 84 | D24: 101 | E24: 95 | F24: 90 | G24: 80 | H24: 119 | I24: 96 | J24: 71 | K24: 81
A25: Debt-to-Equity Ratio | B25: =B12/B3 -> 0.088148461 | C25: =C12/C3 -> 0.049501916 | D25: =D12/D3 -> 0.07364545 | E25: =E12/E3 -> 0.063376932 | F25: =F12/F3 -> 0.13938754 | G25: =G12/G3 -> 0.11035436 | H25: =H12/H3 -> 0.085350617 | I25: =I12/I3 -> 0.11490841 | ... K25: =K12/K3 -> 0.13209461

Sheet Phase 2_Ratio Analysis & Trend
B1: FY 2015 | C1: FY 2016 | D1: FY 2017 | E1: FY 2018 | F1: FY 2019 | G1: FY 2020 | H1: FY 2021 | I1: FY 2022 | J1: FY 2023 | K1: FY 2024
A2: PAT | B2: 1427 | C2: 1803 | D2: 2016 | E2: 2098 | F2: 2208 | G2: 2774 | H2: 3207 | I2: 3085 | J2: 4195 | K2: 5558
A3: Shareholder's Equity | B3: =(96+4646) -> 4742 | C3: =(96+6429) -> 6525 | D3: =(96+7508) -> 7604 | E3: =(96+8314) -> 8410 | F3: =(96+9374) -> 9470 | G3: =(96+10035) -> 10131 | H3: =(96+12710) -> 12806 | I3: =(96+13715) -> 13811 | J3: =(96+15896) -> 15992 | K3: =(96+18633) -> 18729
A4: Total Assets | B4: 8914 | C4: 10559 | D4: 12405 | E4: 13763 | F4: 16249 | G4: 16138 | H4: 20355 | I4: 22958 | J4: 25779 | K4: 29901
A5: PBT | B5: 1935 | C5: 2400 | D5: 2622 | E5: 2803 | F5: 3033 | G5: 3280 | H5: 3973 | I5: 4065 | J5: 3988 | K5: 5402
A6: Interest | B6: 42 | C6: 49 | D6: 37 | E6: 41 | F6: 110 | G6: 102 | H6: 92 | I6: 95 | J6: 144 | K6: 205
A7: EBIT | B7: 1977 | C7: 2449 | D7: 2659 | E7: 2844 | F7: 3143 | G7: 3382 | H7: 4065 | I7: 3988 | J7: 5402 | K7: 6732
A8: Other Liabilities | B8: 3754 | C8: 3711 | D8: 4241 | E8: 4820 | F8: 5459 | G8: 4889 | H8: 6456 | I8: 7560 | J8: 7854 | K8: 8698
A9: ROE | B9: =B2/B3*100 -> 30.092788 | C9: =C2/C3*100 -> 27.632184 | D9: =D2/D3*100 -> 26.512362 | E9: =E2/E3*100 -> 24.946492 | F9: =F2/F3*100 -> 23.315734 | G9: =G2/G3*100 -> 27.381305 | H9: =H2/H3*100 -> 25.042949 | I9: =I2/I3*100 -> 22.337267 | ... K9: =K2/K3*100 -> 29.675904 | M9: =B2/B3*100 -> 30.092788
A10: ROA | B10: =B2/B4*100 -> 16.008526 | C10: =C2/C4*100 -> 17.075481 | D10: =D2/D4*100 -> 16.251511 | E10: =E2/E4*100 -> 15.24377 | F10: =F2/F4*100 -> 13.588529 | G10: =G2/G4*100 -> 17.189243 | H10: =H2/H4*100 -> 15.755343 | I10: =I2/I4*100 -> 13.437582 | ... K10: =K2/K4*100 -> 18.588007
A11: ROCE | B11: =B7/(B4-B8)*100 -> 38.313953 | C11: =C7/(C4-C8)*100 -> 35.762266 | D11: =D7/(D4-D8)*100 -> 32.569819 | E11: =E7/(E4-E8)*100 -> 31.801409 | F11: =F7/(F4-F8)*100 -> 29.128823 | G11: =G7/(G4-G8)*100 -> 30.064895 | H11: =H7/(H4-H8)*100 -> 29.246708 | I11: =I7/(I4-I8)*100 -> 25.899467 | ... K11: =K7/(K4-K8)*100 -> 31.750224
A12: Toral Borrowings | B12: 418 | C12: 323 | D12: 560 | E12: 533 | F12: 1320 | G12: 1118 | H12: 1093 | I12: 1587 | J12: 1933 | K12: 2474
A13: Debt-to- Equity | B13: =B12/B3 -> 0.088148461 | C13: =C12/C3 -> 0.049501916 | D13: =D12/D3 -> 0.07364545 | E13: =E12/E3 -> 0.063376932 | F13: =F12/F3 -> 0.13938754 | G13: =G12/G3 -> 0.11035436 | H13: =H12/H3 -> 0.085350617 | I13: =I12/I3 -> 0.11490841 | ... K13: =K12/K3 -> 0.13209461
A14: Interest Coverage | B14: =B7/B6 -> 47.071429 | C14: =C7/C6 -> 49.979592 | D14: =D7/D6 -> 71.864865 | E14: =E7/E6 -> 69.365854 | F14: =F7/F6 -> 28.572727 | G14: =G7/G6 -> 33.156863 | H14: =H7/H6 -> 44.184783 | I14: =I7/I6 -> 41.978947 | ... K14: =K7/K6 -> 32.839024
A15: EBITDA | B15: 2243 | C15: 2725 | D15: 2994 | E15: 3204 | F15: 3765 | G15: 4162 | H15: 4856 | I15: 4804 | J15: 6260 | K15: 7585
A16: Revenue | B16: 13615 | C16: 14271 | D16: 15062 | E16: 16825 | F16: 19240 | G16: 20211 | H16: 21713 | I16: 29101 | J16: 34389 | K16: 35495
A17: Operating Margin | B17: =B15/B16*100 -> 16.474477 | C17: =C15/C16*100 -> 19.094668 | D17: =D15/D16*100 -> 19.877838 | E17: =E15/E16*100 -> 19.043091 | F17: =F15/F16*100 -> 19.568607 | G17: =G15/G16*100 -> 20.592747 | H17: =H15/H16*100 -> 22.364482 | I17: =I15/I16*100 -> 16.508024 | ... K17: =K15/K16*100 -> 21.369207
A18: Net Profit Margin | B18: =B2/B16*100 -> 10.481087 | C18: =C2/C16*100 -> 12.634013 | D18: =D2/D16*100 -> 13.384677 | E18: =E2/E16*100 -> 12.469539 | F18: =F2/F16*100 -> 11.476091 | G18: =G2/G16*100 -> 13.725199 | H18: =H2/H16*100 -> 14.769953 | I18: =I2/I16*100 -> 10.60101 | ... K18: =K2/K16*100 -> 15.658543
D19: Formula used : ROE = PAT ÷ Shareholders’ Equity × 100 ROA = PAT ÷ Total Assets × 100 ROCE = EBIT ÷ (Total Assets − Other Liabilities) × 100

Sheet Phase 1_Cash Flow
B1: FY 2015 | C1: FY 2016 | D1: FY 2017 | E1: FY 2018 | F1: FY 2019 | G1: FY 2020 | H1: FY 2021 | I1: FY 2022 | J1: FY 2023 | K1: FY 2024
A2: Cash from Operating Activities | B2: 1188 | C2: 2243 | D2: 1527 | E2: 2113 | F2: 2470 | G2: 3038 | H2: 3683 | I2: 986 | J2: 4193 | K2: 6104
A3: Cash from Investing Activities | B3: -465 | C3: -866 | D3: -681 | E3: -1556 | F3: -918 | G3: -518 | H3: -541 | I3: -317 | J3: -1282 | K3: -2548
A4: Cash from Financing Activities | B4: -576 | C4: -849 | D4: -756 | E4: -1379 | F4: -1117 | G4: -2871 | H4: -650 | I4: -1808 | J4: -2140 | K4: -2982
